tests/utils.py
tests/test_workflow_syntax.py
tests/__init__.py
tests/test_statement_syntax.py
tests/test_benchmark.py
fugue_sql_antlr-0.0.1.dist-info/WHEEL
fugue_sql_antlr-0.0.1.dist-info/METADATA
fugue_sql_antlr-0.0.1.dist-info/LICENSE
fugue_sql_antlr-0.0.1.dist-info/RECORD
fugue_sql_antlr-0.0.1.dist-info/top_level.txt
fugue_sql_antlr/parse.py
fugue_sql_antlr/__init__.py
fugue_sql_antlr/constants.py
fugue_sql_antlr/_parser/__init__.py
fugue_sql_antlr/_parser/fugue_sqlLexer.py
fugue_sql_antlr/_parser/sa_fugue_sql.py
fugue_sql_antlr/_parser/fugue_sqlVisitor.py
fugue_sql_antlr/_parser/sa_fugue_sql_cpp_parser.cpython-38-i386-linux-gnu.so
fugue_sql_antlr/_parser/fugue_sqlParser.py
fugue_sql_antlr/_parser/cpp/fugue_sql.interp
fugue_sql_antlr/_parser/cpp/fugue_sqlLexer.cpp
fugue_sql_antlr/_parser/cpp/fugue_sqlLexer.tokens
fugue_sql_antlr/_parser/cpp/fugue_sqlLexer.interp
fugue_sql_antlr/_parser/cpp/fugue_sqlParser.h
fugue_sql_antlr/_parser/cpp/sa_fugue_sql_translator.cpp
fugue_sql_antlr/_parser/cpp/fugue_sqlVisitor.h
fugue_sql_antlr/_parser/cpp/sa_fugue_sql_cpp_parser.cpp
fugue_sql_antlr/_parser/cpp/fugue_sqlLexer.h
fugue_sql_antlr/_parser/cpp/fugue_sql.tokens
fugue_sql_antlr/_parser/cpp/sa_fugue_sql_translator.h
fugue_sql_antlr/_parser/cpp/fugue_sqlParser.cpp
fugue_sql_antlr/_parser/cpp/speedy_antlr.cpp
fugue_sql_antlr/_parser/cpp/fugue_sqlBaseVisitor.cpp
fugue_sql_antlr/_parser/cpp/fugue_sqlBaseVisitor.h
fugue_sql_antlr/_parser/cpp/fugue_sqlVisitor.cpp
fugue_sql_antlr/_parser/cpp/speedy_antlr.h
fugue_sql_antlr/antlr4-cpp-runtime/Token.cpp
fugue_sql_antlr/antlr4-cpp-runtime/TokenStreamRewriter.cpp
fugue_sql_antlr/antlr4-cpp-runtime/InputMismatchException.cpp
fugue_sql_antlr/antlr4-cpp-runtime/ProxyErrorListener.h
fugue_sql_antlr/antlr4-cpp-runtime/ListTokenSource.h
fugue_sql_antlr/antlr4-cpp-runtime/TokenStream.cpp
fugue_sql_antlr/antlr4-cpp-runtime/DefaultErrorStrategy.h
fugue_sql_antlr/antlr4-cpp-runtime/BaseErrorListener.cpp
fugue_sql_antlr/antlr4-cpp-runtime/Vocabulary.cpp
fugue_sql_antlr/antlr4-cpp-runtime/Parser.cpp
fugue_sql_antlr/antlr4-cpp-runtime/CommonToken.cpp
