Metadata-Version: 2.1
Name: fugue-sql-antlr
Version: 0.0.1
Summary: Fugue SQL Antlr Parser
Home-page: http://github.com/fugue-project/fugue
Author: The Fugue Development Team
Author-email: hello@fugue.ai
License: Apache-2.0
Keywords: distributed spark dask sql dsl domain specific language
Platform: UNKNOWN
Classifier: Development Status :: 5 - Production/Stable
Classifier: Intended Audience :: Developers
Classifier: Topic :: Software Development :: Libraries :: Python Modules
Classifier: License :: OSI Approved :: Apache Software License
Classifier: Programming Language :: Python :: 3
Classifier: Programming Language :: Python :: 3.6
Classifier: Programming Language :: Python :: 3.7
Classifier: Programming Language :: Python :: 3.8
Classifier: Programming Language :: Python :: 3.9
Classifier: Programming Language :: Python :: 3.10
Classifier: Programming Language :: Python :: 3 :: Only
Requires-Python: >=3.6
License-File: LICENSE
Requires-Dist: triad
Requires-Dist: antlr4-python3-runtime (>=4.9.3)
Requires-Dist: jinja2
Provides-Extra: test
Requires-Dist: speedy-antlr-tool ; extra == 'test'
